{
  "dayNum": 6,
  "storeName": "tourdivide06",
  "backgroundImg": "img/tourdivide/day06/day06pic00.JPG",
  "h2": "Day 06 - Two long passes and a long ride into Whitefish, MT",
  "h3": "Riding, Walking and more tire woes",
  "date": "Sunday, June 14, 2015 Eureka to Whitefish, MT",
  "stats": "left at 6:57am, 9hr28m, 94.7 miles, 5,833 ft of climbing",
  "elevSumm": "elev/20150614summ.png",
  "elevElev": "elev/20150614elev.png",
  "elevEarth": "",
  "mapMid": "z16rO1nf9OsU.k-PI-urLMEWE",
  "flickr": "https://flic.kr/s/aHsk9CwBC1",
  "intro": "<blockquote>For someone who doesn't like hills you picked a strange race to join\n\t\t\t\t\t</blockquote>\n\t\t\t\t\t<h2 class=\"section-heading\">Eureka to Whitefish, MT</h2>\n\t\t\t\t\t<p>\n\t\t\t\t\t\tThis was my longest day so far and it had two pretty significant climbs. It was also the first time I had\n\t\t\t\t\t\tother riders around me. The cover photo above is from the approach to Red Meadow Lake. Everyone who passed\n\t\t\t\t\t\tme eventually walked.\n\t\t\t\t\t</p>\n\t\t\t\t\t<blockquote>Once again - Mornings are for going up - twenty plus miles\n\t\t\t\t\t</blockquote>\n\t\t\t\t\t<div>\n\t\t\t\t\t\t<img class=\"img-responsive\" src=\"elev/20150614Eureka_whitefish.JPG\" alt=\"\" style=\"width:95%\">\n\t\t\t\t\t</div>",
  "prevDay": 5,
  "nextDay": 7,
  "content": ""
}