{
  "dayNum": 13,
  "storeName": "tourdivide13",
  "backgroundImg": "img/tourdivide/day13/day13pic00.JPG",
  "h2": "Day 13 - Rerouting to Jim's Tour Divide",
  "h3": "Chocolate Milk at Great Divide Outfitters",
  "date": "Sunday, June 21, 2015 Butte to Wise River, MT",
  "stats": "8:45 AM, 8h57min, 50.60 miles, 2,960 ft of climbing",
  "elevSumm": "elev/20150621summ.png",
  "elevElev": "elev/20150621elev.png",
  "elevEarth": "",
  "mapMid": "z16rO1nf9OsU.kQFVh1gMgHlU",
  "flickr": "https://flic.kr/s/aHsk9CwBC1",
  "intro": "<blockquote>Taking the road less traveled by TD riders\n\t\t\t\t\t</blockquote>\n\t\t\t\t\t<h2 class=\"section-heading\">Alternative routes</h2>\n\n\t\t\t\t\t<a href=\"#\">\n\t\t\t\t\t\t<img class=\"img-responsive\" src=\"img/tourdivide/day13/day13pic01.JPG\" alt=\"\">\n\t\t\t\t\t\t<span>\n                                    <a href=\"#\" class=\"caption text-muted\">caption\n                                    </a>\n                                </span>\n\t\t\t\t\t</a>\n\t\t\t\t\t<p>\n\t\t\t\t\t\tThe road out of Butte was paved for the first 10 miles. Once I was off the main state highway the road\n\t\t\t\t\t\tturned up for the next 8 miles.\n\t\t\t\t\t</p>",
  "prevDay": 12,
  "nextDay": 14,
  "content": "<a href=\"#\">\n\t\t\t\t\t\t\n\t\t\t\t\t\t\n\t\t\t\t\t</a>\n\t\t\t\t\t<p>\n\t\t\t\t\t\tThe giant mine in the hills behind Butte. I didn't notice them until I got to this vantage point since I had\n\t\t\t\t\t\tapproached the city from the north and traveled around the mines and slag pits.\n\t\t\t\t\t\t<a href=\"#\">\n\t\t\t\t\t\t\t<img class=\"img-responsive\" src=\"img/tourdivide/day13/day13pic03.JPG\" alt=\"\" width=\"95%\">\n\t\t\t\t\t\t</a>\n\t\t\t\t\t<p>\n\t\t\t\t\t\tThis pass took you out of the Butte water shed and over the continental divide.\n\t\t\t\t\t</p>\n\t\t\t\t\t<a href=\"#\">\n\t\t\t\t\t\t<img class=\"img-responsive\" src=\"img/tourdivide/day13/day13pic02.JPG\" alt=\"\" width=\"95%\">\n\t\t\t\t\t</a>\n\t\t\t\t\t</p>\n\t\t\t\t\t<h2 class=\"section-heading\">Another Divide Crossing</h2>\n\t\t\t\t\t<div class=\"col-sm-12 blog-post\">\n\t\t\t\t\t\t<div class=\"col-sm-6\">\n\t\t\t\t\t\t\t<a href=\"#\">\n\t\t\t\t\t\t\t\t<img class=\"img-responsive\" src=\"img/tourdivide/day13/day13pic04.JPG\" alt=\"\" width=\"100%\">\n\t\t\t\t\t\t\t</a>\n\t\t\t\t\t\t</div>\n\t\t\t\t\t\t<div class=\"col-sm-6\">\n\t\t\t\t\t\t\t<a href=\"#\">\n\t\t\t\t\t\t\t\t<img class=\"img-responsive\" src=\"img/tourdivide/day13/day13pic05.JPG\" alt=\"\" width=\"100%\">\n\t\t\t\t\t\t\t</a>\n\t\t\t\t\t\t</div>\n\t\t\t\t\t</div>\n\t\t\t\t\t<div class=\"col-sm-12 blog-post\">\n\t\t\t\t\t\t<div class=\"col-sm-6\">\n\t\t\t\t\t\t\t<a href=\"#\">\n\t\t\t\t\t\t\t\t<img class=\"img-responsive\" src=\"img/tourdivide/day13/day13pic06.JPG\" alt=\"\" width=\"100%\">\n\t\t\t\t\t\t\t\t<a href=\"#\" class=\"caption text-muted\">Lava or Glacier formations\n\t\t\t\t\t\t\t\t</a>\n\t\t\t\t\t\t\t</a>\n\t\t\t\t\t\t</div>\n\t\t\t\t\t\t<div class=\"col-sm-6\">\n\t\t\t\t\t\t\t<p>\n\t\t\t\t\t\t\t\tThe top of this pass went on for a while. There was a campground on the top and before\n\t\t\t\t\t\t\t\tthe trail dropped off I stopped for lunch and a break.\n\t\t\t\t\t\t\t</p>\n\t\t\t\t\t\t</div>\n\t\t\t\t\t</div>\n\t\t\t\t\t<hr>\n\t\t\t\t\t<a href=\"#\">\n\t\t\t\t\t\t<img class=\"img-responsive\" src=\"img/tourdivide/day13/day13pic07.JPG\" alt=\"\">\n\t\t\t\t\t</a>\n\n\t\t\t\t\t<p>\n\t\t\t\t\t\tThe trail then started down and became a white knuckle adventure all the way down to the interstate highway.\n\t\t\t\t\t\tSome very steep downhills with just enough curves to make your hands numb while you tried to hold onto your\n\t\t\t\t\t\tbrakes. I heard later in the day I rider had fallen and broken their collar bone.\n\t\t\t\t\t</p>\n\t\t\t\t\t<a href=\"#\">\n\t\t\t\t\t\t<img class=\"img-responsive\" src=\"img/tourdivide/day13/day13pic08.JPG\" alt=\"\">\n\t\t\t\t\t</a>\n\n\n\t\t\t\t\t<a href=\"#\">\n\t\t\t\t\t\t<img class=\"img-responsive\" src=\"img/tourdivide/day13/day13pic09.JPG\" alt=\"\">\n\t\t\t\t\t</a>\n\t\t\t\t\t<h2 class=\"section-heading\">Taking the easy way to \"Jim's Tour Divide\"</h2>\n\t\t\t\t\t<p>\n\t\t\t\t\t\tThis was where I took my first \"alternate\". Up until this point I had followed the TD race path 100%\n\t\t\t\t\t\tover some pretty rough terrain. Coming up on the race map was a place called Fleecer Ridge which supposedly\n\t\t\t\t\t\thad a 18% downhill grade. On the ACA maps there was an alternate route along two state highways. These\n\t\t\t\t\t\tlooked\n\t\t\t\t\t\tpretty easy so I decided to take this eighteen mile alternate instead of about 23 over the mountain.\n\t\t\t\t\t</p>\n\t\t\t\t\t<div class=\"col-sm-12 blog-post\">\n\t\t\t\t\t\t<div class=\"col-sm-6\">\n\t\t\t\t\t\t\t<p><a href=\"http://www.bigholetrout.com\">Great Divide Outfitters</a>\n\t\t\t\t\t\t\t\tAfter following the I15 frontage road for 10 miles (I would take this road again during the end of my\n\t\t\t\t\t\t\t\tride into Lima).\n\t\t\t\t\t\t\t\tWhen I turned onto Rt 47 I hadn't stopped for most the day. So mostly to get off the bike I stopped at\n\t\t\t\t\t\t\t\t<a href=\"http://www.bigholetrout.com/\">Great Divide Outfitters </a>\n\t\t\t\t\t\t\t</p>\n\t\t\t\t\t\t</div>\n\t\t\t\t\t\t<div class=\"col-sm-6\">\n\t\t\t\t\t\t\t<p><a href=\"#\">\n\t\t\t\t\t\t\t\t<img class=\"img-responsive\" src=\"img/tourdivide/day13/day13pic10.JPG\" alt=\"\" width=\"100%\">\n\t\t\t\t\t\t\t\t<span>\n                                            <a href=\"http://www.bigholetrout.com\" class=\"caption text-muted\">Great Divide Outfitters\n                                            </a>\n                                        </span>\n\t\t\t\t\t\t\t</a>\n\t\t\t\t\t\t\t</p>\n\t\t\t\t\t\t</div>\n\t\t\t\t\t</div>\n\t\t\t\t\t<div class=\"col-sm-12 blog-post\">\n\t\t\t\t\t\t<div class=\"col-sm-6\">\n\t\t\t\t\t\t\t<p>\n\t\t\t\t\t\t\t\t<img class=\"img-responsive\" src=\"img/tourdivide/day13/day13pic15.JPG\" alt=\"\" width=\"100%\">\n\t\t\t\t\t\t\t\t<span><a href=\"http://www.bigholetrout.com\"\n\t\t\t\t\t\t\t\t         class=\"caption text-muted\">Great Divide Outfitters</a></span>\n\t\t\t\t\t\t\t</p>\n\t\t\t\t\t\t</div>\n\t\t\t\t\t\t<div class=\"col-sm-6\">\n\t\t\t\t\t\t\t<p>\n\t\t\t\t\t\t\t\tStopped in the fly shop. Had a nice time talking with John and another local about the area.\n\t\t\t\t\t\t\t\tI was looking for something to drink and John brought out his own milk and Hersey's chocolate syrup\n\t\t\t\t\t\t\t\tso I could make some chocolate milk which fueled me into the wind on the ride up to Wise River.\n\t\t\t\t\t\t\t</p>\n\t\t\t\t\t\t</div>\n\t\t\t\t\t</div>\n\t\t\t\t\t\t<img class=\"img-responsive\" src=\"img/tourdivide/day13/day13pic11.JPG\" alt=\"\">\n\t\t\t\t\t<p>\n\t\t\t\t\t\tMostly into the wind and trying to beat the rain coming with the wind. There were some of the first clouds I\n\t\t\t\t\t\thad seen in Montana. I was happy when my garmin rejoined the official trail which meant I only had two miles\n\t\t\t\t\t\tto the Wise River Club.\n\t\t\t\t\t</p>\n\t\t\t\t\t\t<img class=\"img-responsive\" src=\"img/tourdivide/day13/day13pic12.JPG\" alt=\"\">\n\t\t\t\t\t<p>Passed these old buildings and the river meandered up with many fisherman and fishing camps along the\n\t\t\t\t\t\tway.</p>\n\t\t\t\t\t\t<img class=\"img-responsive\" src=\"img/tourdivide/day13/day13pic13.JPG\" alt=\"\">\n\t\t\t\t\t<h2 class=\"section-heading\">Wise River Club</h2>\n\t\t\t\t\t<p>\n\t\t\t\t\t\tI got a room for the night and had dinner with Mike from Washington whom I had last seen in Ovando. His tour\n\t\t\t\t\t\twas done\n\t\t\t\t\t\tafter hurting his knee on the ride / walk down from Fleecer Ridge. He was getting a ride from the hotel\n\t\t\t\t\t\tmanager the next\n\t\t\t\t\t\tday back to Butte so his wife could pick him up.\n\t\t\t\t\t</p>\n\t\t\t\t\t<a href=\"#\">\n\t\t\t\t\t\t<img class=\"img-responsive\" src=\"img/tourdivide/day13/day13pic14.JPG\" alt=\"\">\n\t\t\t\t\t</a>\n\t\t\t\t\t<a href=\"http://www.wiseriverclub.com\" class=\"caption text-muted\">Wise River Club\n\t\t\t\t\t</a>\n\t\t\t\t\t<h2 class=\"section-heading\">New Objective - Ride from Banff Alberta to across the Mexico border</h2>\n\t\t\t\t\t<p>\n\t\t\t\t\t\tI guess this was the goal all along. When I finally realized this it took a load off my mind. I had decided\n\t\t\t\t\t\tI didn't need to stick rigidly to the Race Map. I would be leaving the safety of the purple line. I had to\n\t\t\t\t\t\tfind some\n\t\t\t\t\t\troutes and take some chances without having all the details my maps and devises gave me.\n\t\t\t\t\t\tEven the ACA maps don't give you much help off the path since the cue sheets cover much of the maps.\n\t\t\t\t\t\t<br>\n\t\t\t\t\t\t<br>\n\t\t\t\t\t\tIt allowed me to have more fun and make some time instead of slogging along through potentially really\n\t\t\t\t\t\tmuddy or steep sections. It also allowed me to slow down and not worry so much about where I was going to\n\t\t\t\t\t\tget to the next day. In the days ahead I would venture off the main trail and see some really great sections\n\t\t\t\t\t\tof the areas around the TD course. Generally I made it back to the route by the end of the day where I met\n\t\t\t\t\t\tother riders.\n\t\t\t\t\t\t<br>\n\t\t\t\t\t\t<br>\n\t\t\t\t\t\tAfter 13 days on the road and seeing numerous people quit the race I decided to follow a path of lesser\n\t\t\t\t\t\tresistance while still trying to stay on the course as much as I could.\n\t\t\t\t\t</p>\n\n\t\t\t\t\t\n\t\t\t\t\t\n\t\t\t\t\t<a href=\"https://www.google.com/maps/d/embed?mid=z16rO1nf9OsU.kQFVh1gMgHlU&usp=sharing\">\n\t\t\t\t\t\tSee full screen map\n\t\t\t\t\t</a>\n\t\t\t\t\t\n\n\t\t\t\t\t<p>Text by <a href=\"http://www.havingadventures.com/\">Jim O'Brien</a>\n\t\t\t\t\t\t. Photographs by Jim O'Brien<a href=\"https://flic.kr/s/aHsk9CwBC1\">TD on Flickr</a>.</p>"
}